edge/__init__.py
edge/config.py
edge/dvc.py
edge/enable_api.py
edge/endpoint.py
edge/exception.py
edge/gcloud.py
edge/path.py
edge/sacred.py
edge/state.py
edge/storage.py
edge/train.py
edge/tui.py
edge/versions.py
edge/vertex_deploy.py
edge/command/__init__.py
edge/command/force_unlock.py
edge/command/init.py
edge/command/common/__init__.py
edge/command/common/precommand_check.py
edge/command/config/__init__.py
edge/command/config/subparser.py
edge/command/dvc/__init__.py
edge/command/dvc/init.py
edge/command/dvc/subparser.py
edge/command/experiments/__init__.py
edge/command/experiments/get_dashboard.py
edge/command/experiments/get_mongodb.py
edge/command/experiments/init.py
edge/command/experiments/subparser.py
edge/command/model/__init__.py
edge/command/model/deploy.py
edge/command/model/describe.py
edge/command/model/get_endpoint.py
edge/command/model/init.py
edge/command/model/list.py
edge/command/model/remove.py
edge/command/model/subparser.py
edge/command/model/template.py
edge/k8s/__init__.py
edge/k8s/omniboard.yaml
edge/templates/tensorflow_model/cookiecutter.json
edge/templates/tensorflow_model/{{cookiecutter.model_name}}/__init__.py
edge/templates/tensorflow_model/{{cookiecutter.model_name}}/train.py
vertex_edge-0.1.118.data/scripts/edge
vertex_edge-0.1.118.data/scripts/vertex_edge.py
vertex_edge-0.1.118.dist-info/LICENSE
vertex_edge-0.1.118.dist-info/METADATA
vertex_edge-0.1.118.dist-info/WHEEL
vertex_edge-0.1.118.dist-info/top_level.txt
vertex_edge-0.1.118.dist-info/RECORD
