Metadata-Version: 2.1
Name: vertex-edge
Version: 0.1.118
Summary: UNKNOWN
Home-page: https://github.com/fuzzylabs/vertex-edge
License: UNKNOWN
Platform: UNKNOWN
License-File: LICENSE
Requires-Dist: pyserde (==0.4.0)
Requires-Dist: google-cloud-container (==2.4.1)
Requires-Dist: google-cloud-secret-manager (==2.5.0)
Requires-Dist: google-cloud-aiplatform (==1.1.1)
Requires-Dist: google-cloud-storage (==1.38.0)
Requires-Dist: cookiecutter (==1.7.3)
Requires-Dist: sacred (==0.8.2)
Requires-Dist: pymongo (==3.11.4)
Requires-Dist: questionary (==1.10.0)
